src/BC.v
module BC(
    input inicio,
    input clk,
    input reset,
    output reg LX,
    output reg LS,
    output reg LH,
    output reg Hula,
    output reg[1:0] M0,
    output reg[1:0] M1,
    output reg[1:0] M2
);

reg[4:0] state;

parameter A = 5'b00000, B = 5'b00001, C = 5'b00010, D = 5'b00011, E = 5'b00100, F = 5'b00101, G = 5'b00110, H = 5'b00111, I = 5'b01000, J = 5'b01001, K = 5'b01010, L = 5'b01011, M = 5'b01100, N = 5'b01101, O = 5'b01110, P = 5'b01111, Q = 5'b10000, R = 5'b10001, S = 5'b10010, T = 5'b10011;

always @(posedge clk or reset)begin
    if (reset == 1 || inicio == 0) begin
        M0 <= 0;
        LX <= 0;
        M1 <= 0;
        M2 <= 0;
        Hula <= 0;
        LS <= 0;
        LH <= 0;
        state <= A;
    end
    else if (inicio == 1) begin
        case (state)
            A: begin
                M0 <= 0;
                LX <= 1;
                M1 <= 0;
                M2 <= 0;
                Hula <= 0;
                LS <= 0;
                LH <= 0;
                state <= B;
            end
            B: begin
                M0 <= 0;
                LX <= 0;
                M1 <= 1;
                M2 <= 0;
                Hula <= 0;
                LS <= 0;
                LH <= 0;
                state <= C;
            end
            C: begin
                M0 <= 0;
                LX <= 0;
                M1 <= 1;
                M2 <= 0;
                Hula <= 1;
                LS <= 0;
                LH <= 0;
                state <= D;
                end                    
            D: begin
                M0 <= 0;
                LX <= 0;
                M1 <= 1;
                M2 <= 0;
                Hula <= 1;
                LS <= 0;
                LH <= 1;
                state <= E;
            end
            E: begin
                M0 <= 1;
                LX <= 0;
                M1 <= 0;
                M2 <= 0;
                Hula <= 0;
                LS <= 0;
                LH <= 0;
                state <= F;
            end
            F: begin
                M0 <= 1;
                LX <= 0;
                M1 <= 0;
                M2 <= 3;
                Hula <= 0;
                LS <= 0;
                LH <= 0;
                state <= G;
            end
            G: begin
                M0 <= 1;
                LX <= 0;
                M1 <= 0;
                M2 <= 3;
                Hula <= 1;
                LS <= 0;
                LH <= 0;
                state <= H;
            end
            H: begin
                M0 <= 1;
                LX <= 0;
                M1 <= 0;
                M2 <= 3;
                Hula <= 1;
                LS <= 0;
                LH <= 1;
                state <= I;
            end
            I: begin
                M0 <= 2;
                LX <= 0;
                M1 <= 0;
                M2 <= 0;
                Hula <= 0;
                LS <= 0;
                LH <= 0;
                state <= J;
            end
            J: begin
                M0 <= 2;
                LX <= 0;
                M1 <= 0;
                M2 <= 0;
                Hula <= 0;
                LS <= 0;
                LH <= 0;
                state <= K;
            end
            K: begin
                M0 <= 2;
                LX <= 0;
                M1 <= 0;
                M2 <= 0;
                Hula <= 1;
                LS <= 0;
                LH <= 0;
                state <= L;
            end
            L: begin
                M0 <= 2;
                LX <= 0;
                M1 <= 0;
                M2 <= 0;
                Hula <= 1;
                LS <= 1;
                LH <= 0;
                state <= M;
            end
            M: begin
                M0 <= 0;
                LX <= 0;
                M1 <= 2;
                M2 <= 3;
                Hula <= 0;
                LS <= 0;
                LH <= 0;
                state <= N;
            end
            N: begin
                M0 <= 0;
                LX <= 0;
                M1 <= 2;
                M2 <= 3;
                Hula <= 0;
                LS <= 0;
                LH <= 0;
                state <= O;
            end
            O: begin
                M0 <= 0;
                LX <= 0;
                M1 <= 0;
                M2 <= 3;
                Hula <= 0;
                LS <= 0;
                LH <= 1;
                state <= P;
            end
            P: begin
                M0 <= 3;
                LX <= 0;
                M1 <= 0;
                M2 <= 0;
                Hula <= 0;
                LS <= 0;
                LH <= 0;
                state <= Q;
            end
            Q: begin
                M0 <= 3;
                LX <= 0;
                M1 <= 0;
                M2 <= 3;
                Hula <= 0;
                LS <= 0;
                LH <= 0;
                state <= R;
            end
            R: begin
                M0 <= 3;
                LX <= 0;
                M1 <= 0;
                M2 <= 3;
                Hula <= 0;
                LS <= 0;
                LH <= 0;
                state <= S;
            end
            S: begin
                M0 <= 3;
                LX <= 0;
                M1 <= 0;
                M2 <= 3;
                Hula <= 0;
                LS <= 1;
                LH <= 0;
                state <= T;
            end
            T: begin
                M0 <= 0;
                LX <= 0;
                M1 <= 0;
                M2 <= 0;
                Hula <= 0;
                LS <= 0;
                LH <= 0;
                state <= A;
            end
        endcase
    end
end

endmodule

module testbench;

    reg inicio0 = 0;
    reg clk0 = 0;
    reg reset0 = 0;
    wire LX0;
    wire LS0;
    wire LH0;
    wire H0;
    wire [1:0] M00;
    wire [1:0] M10;
    wire [1:0] M20;

BC jose(inicio0, clk0, reset0, LX0, LS0, LH0, H0, M00, M10, M20);

always #1 begin
    clk0 <= ~clk0;
end

initial begin
    $dumpvars;
    reset0 = 1;
    #2;
    reset0 = 0;
    inicio0 = 1;
    #100;
    $finish;
end
endmodule

src/dump.vcd
$date
	Tue Mar 29 12:50:57 2022
$end
$version
	Icarus Verilog
$end
$timescale
	1s
$end
$scope module testbench $end
$var wire 2 ! M20 [1:0] $end
$var wire 2 " M10 [1:0] $end
$var wire 2 # M00 [1:0] $end
$var wire 1 $ LX0 $end
$var wire 1 % LS0 $end
$var wire 1 & LH0 $end
$var wire 1 ' H0 $end
$var reg 1 ( clk0 $end
$var reg 1 ) inicio0 $end
$var reg 1 * reset0 $end
$scope module jose $end
$var wire 1 ( clk $end
$var wire 1 ) inicio $end
$var wire 1 * reset $end
$var reg 1 ' Hula $end
$var reg 1 & LH $end
$var reg 1 % LS $end
$var reg 1 $ LX $end
$var reg 2 + M0 [1:0] $end
$var reg 2 , M1 [1:0] $end
$var reg 2 - M2 [1:0] $end
$var reg 5 . state [4:0] $end
$upscope $end
$upscope $end
$enddefinitions $end
#0
$dumpvars
b0 .
b0 -
b0 ,
b0 +
1*
0)
0(
0'
0&
0%
0$
b0 #
b0 "
b0 !
$end
#1
1(
#2
b1 .
1$
0(
1)
0*
#3
b10 .
b1 "
b1 ,
0$
1(
#4
0(
#5
b11 .
1'
1(
#6
0(
#7
b100 .
1&
1(
#8
0(
#9
b101 .
0&
0'
b0 "
b0 ,
b1 #
b1 +
1(
#10
0(
#11
b110 .
b11 !
b11 -
1(
#12
0(
#13
b111 .
1'
1(
#14
0(
#15
b1000 .
1&
1(
#16
0(
#17
b1001 .
0&
0'
b0 !
b0 -
b10 #
b10 +
1(
#18
0(
#19
b1010 .
1(
#20
0(
#21
b1011 .
1'
1(
#22
0(
#23
b1100 .
1%
1(
#24
0(
#25
b1101 .
0%
0'
b11 !
b11 -
b10 "
b10 ,
b0 #
b0 +
1(
#26
0(
#27
b1110 .
1(
#28
0(
#29
b1111 .
1&
b0 "
b0 ,
1(
#30
0(
#31
b10000 .
0&
b0 !
b0 -
b11 #
b11 +
1(
#32
0(
#33
b10001 .
b11 !
b11 -
1(
#34
0(
#35
b10010 .
1(
#36
0(
#37
b10011 .
1%
1(
#38
0(
#39
b0 .
0%
b0 !
b0 -
b0 #
b0 +
1(
#40
0(
#41
b1 .
1$
1(
#42
0(
#43
b10 .
b1 "
b1 ,
0$
1(
#44
0(
#45
b11 .
1'
1(
#46
0(
#47
b100 .
1&
1(
#48
0(
#49
b101 .
0&
0'
b0 "
b0 ,
b1 #
b1 +
1(
#50
0(
#51
b110 .
b11 !
b11 -
1(
#52
0(
#53
b111 .
1'
1(
#54
0(
#55
b1000 .
1&
1(
#56
0(
#57
b1001 .
0&
0'
b0 !
b0 -
b10 #
b10 +
1(
#58
0(
#59
b1010 .
1(
#60
0(
#61
b1011 .
1'
1(
#62
0(
#63
b1100 .
1%
1(
#64
0(
#65
b1101 .
0%
0'
b11 !
b11 -
b10 "
b10 ,
b0 #
b0 +
1(
#66
0(
#67
b1110 .
1(
#68
0(
#69
b1111 .
1&
b0 "
b0 ,
1(
#70
0(
#71
b10000 .
0&
b0 !
b0 -
b11 #
b11 +
1(
#72
0(
#73
b10001 .
b11 !
b11 -
1(
#74
0(
#75
b10010 .
1(
#76
0(
#77
b10011 .
1%
1(
#78
0(
#79
b0 .
0%
b0 !
b0 -
b0 #
b0 +
1(
#80
0(
#81
b1 .
1$
1(
#82
0(
#83
b10 .
b1 "
b1 ,
0$
1(
#84
0(
#85
b11 .
1'
1(
#86
0(
#87
b100 .
1&
1(
#88
0(
#89
b101 .
0&
0'
b0 "
b0 ,
b1 #
b1 +
1(
#90
0(
#91
b110 .
b11 !
b11 -
1(
#92
0(
#93
b111 .
1'
1(
#94
0(
#95
b1000 .
1&
1(
#96
0(
#97
b1001 .
0&
0'
b0 !
b0 -
b10 #
b10 +
1(
#98
0(
#99
b1010 .
1(
#100
0(
#101
b1011 .
1'
1(
