src/SomaMultiplica.v
module SomaMultiplica(
    input[15:0] abc,
    input[15:0] xis,
    input H,
    input clk,
    output[15:0] resultado
);

reg[15:0] r;

assign resultado = r;

always @(posedge clk) begin
    if (H == 1)begin
        r <= abc * xis;
    end
    else begin
        r <= abc + xis;
    end
end
endmodule

// module testbench;

//     reg[15:0] abc0;
//     reg[15:0] xis0;
//     reg H0 = 0;
//     reg clk0 = 0;
//     wire[15:0] resultado0;

// SomaMultiplica jose(abc0, xis0, H0, clk0, resultado0);

// always #1 begin
//     clk0 <= ~clk0;
// end

// initial begin
//     $dumpvars;
//     #1;
//     abc0 <= 2;
//     xis0 <= 3;
//     H0 <= 1;
//     #5;
//     $finish;
// end
// endmodule

src/Multiplexador.v
//Multiplexador do Bloco Operativo, será reutilizado em diferentes partes
module Multiplexador(
    input[15:0] A,
    input[15:0] B,
    input[15:0] C,
    input[15:0] D,
    input [1:0] set,
    input clk,
    output[15:0] saidaM
);

reg[15:0] s;

assign saidaM = s;
//A ordem das entradas importa nesse caso para setar as entradas no BO
always @(posedge clk) begin
    if (set == 0)begin
        s <= A;
    end
    if (set == 1)begin
        s <= B;
    end
    if (set == 2) begin
        s <= C;
    end
    if (set == 3) begin
        s <= D;
    end
end
endmodule

// module testbench;

//     reg [15:0] A0;
//     reg [15:0] B0;
//     reg [15:0] C0;
//     reg [15:0] D0;
//     reg [1:0] set0 = 0;
//     reg clk0 = 0;
//     wire [15:0] saida0;

// Multiplexador jose(A0, B0, C0, D0, set0, clk0, saida0);

// always #1 begin
//     clk0 <= ~clk0;
// end

// initial begin
//     $dumpvars;
//     #1;
//     A0 <= 1;
//     B0 <= 0;
//     C0 <= 3;
//     D0 <= 4;
//     set0 <= 1;
//     #5;
//     $finish;
// end
// endmodule

src/Registrador.v
module Registrador(
    input [15:0] D,
    input clk,
    input load,
    input rst,
    output [15:0] Q
);

    reg [15:0] saida;

    assign Q = saida;

    always @(posedge clk or rst) begin
        if (rst == 1) saida <= 0;
        else if (load == 1)begin
        saida <= D;
        end
    end
endmodule

// module testbench;

//     reg [15:0] D0;
//     reg clk0 = 0;
//     reg load0;
//     reg rst0 = 0;
//     wire [15:0] Q0;

// Registrador jose(D0, clk0, load0, rst0, Q0);

// always #1 begin
//     clk0 <= ~clk0;
// end

// initial begin
//     $dumpvars;
//     #1;
//     D0 <= 1;
//     load0 <= 1;
//     #5;
//     load0 <= 0;
//     D0 <= 5;
//     #5;
//     $finish;
// end
// endmodule

src/BO.v
`include "SomaMultiplica.v"
`include "Multiplexador.v"
`include "Registrador.v"

module BO (
    input [15:0] A,
    input [15:0] B,
    input [15:0] C,
    input [1:0] M0,
    input [15:0] x,
    input clk,
    input LX,
    input rst,
    input [1:0] M1,
    input [1:0] M2,
    input LH,
    input LS,
    input H,
    output [15:0] Pronto 
); 

parameter vazio = 16'b0000000000000000;

Registrador R0(x, clk, LX, rst, saidaR0);
wire [15:0] saidaR0;

Registrador R1(saidaSM, clk, LH, rst, saidaR1);
wire [15:0] saidaR1;

Registrador R2(saidaSM, clk, LS, rst, saidaR2);
wire [15:0] saidaR2;

Multiplexador multiplexador0(vazio, A, B, C, M0, clk, saidaM0);
wire [15:0] saidaM0;

Multiplexador multiplexador2(saidaR0, saidaM0, saidaR2, saidaR1, M2, clk, saidaM2);
wire [15:0] saidaM2;

Multiplexador multiplexador1(saidaM0, saidaR0, saidaR2, saidaR1, M1, clk, saidaM1);
wire [15:0] saidaM1;

SomaMultiplica ULA(saidaM1, saidaM2, H, clk, saidaSM);
wire [15:0] saidaSM;

assign Pronto = saidaR2;

endmodule

//module testbench;
//
//    reg [15:0] A0 = 2;
//    reg [15:0] B0 = 2;
//    reg [15:0] C0 = 1;
//    reg [1:0] M00;
//    reg [15:0] x0 = 2;
//    reg clk0 = 0;
//    reg LX0 = 0;
//    reg reset0;
//    reg [1:0] M10;
//    reg [1:0] M20;
//    reg LH0 = 0;
//    reg LS0 = 0;
//    reg H0 = 0;
//    wire [15:0] saida0;
//
//BO jose(A0, B0, C0, M00, x0, clk0, LX0, reset0, M10, M20, LH0, LS0, H0, saida0);
//
//always #1 begin
//    clk0 <= ~clk0;
//end
//
//initial begin
//    $dumpvars;
//    reset0 <= 1;
//    #1;
//    reset0 <= 0;
//    #2;
//    //Estado A
//    M00 <= 00;
//    LX0 <= 1;
//    M10 <= 00;
//    M20 <= 00;
//    H0 <= 0;
//    LS0 <= 0;
//    LH0 <= 0;
//    #2;
//    //Estado B
//    M00 <= 00;
//    LX0 <= 0;
//    M10 <= 01;
//    M20 <= 00;
//    H0 <= 0;
//    LS0 <= 0;
//    LH0 <= 0;
//    #2;
//    //Estado C
//    M00 <= 00;
//    LX0 <= 0;
//    M10 <= 01;
//    M20 <= 00;
//    H0 <= 1;
//    LS0 <= 0;
//    LH0 <= 0;
//    #2;
//    //Estado D
//    M00 <= 00;
//    LX0 <= 0;
//    M10 <= 01;
//    M20 <= 00;
//    H0 <= 1;
//    LS0 <= 0;
//    LH0 <= 1;
//    #2;
//    //Estado E
//    M00 <= 01;
//    LX0 <= 0;
//    M10 <= 00;
//    M20 <= 00;
//    H0 <= 0;
//    LS0 <= 0;
//    LH0 <= 0;
//    #2;
//    //Estado F
//    M00 <= 01;
//    LX0 <= 0;
//    M10 <= 00;
//    M20 <= 11;
//    H0 <= 0;
//    LS0 <= 0;
//    LH0 <= 0;
//    #2;
//    //Estado G
//    M00 <= 01;
//    LX0 <= 0;
//    M10 <= 00;
//    M20 <= 11;
//    H0 <= 1;
//    LS0 <= 0;
//    LH0 <= 0;
//    #2;
//    //Estado H
//    M00 <= 01;
//    LX0 <= 0;
//    M10 <= 00;
//    M20 <= 11;
//    H0 <= 1;
//    LS0 <= 0;
//    LH0 <= 1;
//    #2;
//    //Estado I
//    M00 <= 10;
//    LX0 <= 0;
//    M10 <= 00;
//    M20 <= 00;
//    H0 <= 0;
//    LS0 <= 0;
//    LH0 <= 0;
//    #2;
//    //Estado J
//    M00 <= 10;
//    LX0 <= 0;
//    M10 <= 00;
//    M20 <= 00;
//    H0 <= 0;
//    LS0 <= 0;
//    LH0 <= 0;
//    #2;
//    //Estado K
//    M00 <= 10;
//    LX0 <= 0;
//    M10 <= 00;
//    M20 <= 00;
//    H0 <= 1;
//    LS0 <= 0;
//    LH0 <= 0;
//    #2;
//    //Estado L
//    M00 <= 10;
//    LX0 <= 0;
//    M10 <= 00;
//    M20 <= 00;
//    H0 <= 1;
//    LS0 <= 1;
//    LH0 <= 0;
//    #2;
//    //Estado M
//    M00 <= 00;
//    LX0 <= 0;
//    M10 <= 10;
//    M20 <= 11;
//    H0 <= 0;
//    LS0 <= 0;
//    LH0 <= 0;
//    #2;
//    //Estado N
//    M00 <= 00;
//    LX0 <= 0;
//    M10 <= 10;
//    M20 <= 11;
//    H0 <= 0;
//    LS0 <= 0;
//    LH0 <= 0;
//    #2;
//    //Estado O
//    M00 <= 00;
//    LX0 <= 0;
//    M10 <= 00;
//    M20 <= 11;
//    H0 <= 0;
//    LS0 <= 0;
//    LH0 <= 1;
//    #2;
//    //Estado P
//    M00 <= 11;
//    LX0 <= 0;
//    M10 <= 00;
//    M20 <= 00;
//    H0 <= 0;
//    LS0 <= 0;
//    LH0 <= 0;
//    #2;
//    //Estado Q
//    M00 <= 11;
//    LX0 <= 0;
//    M10 <= 00;
//    M20 <= 11;
//    H0 <= 0;
//    LS0 <= 0;
//    LH0 <= 0;
//    #2;
//    //Estado R
//    M00 <= 11;
//    LX0 <= 0;
//    M10 <= 00;
//    M20 <= 11;
//    H0 <= 0;
//    LS0 <= 0;
//    LH0 <= 0;
//    #2;
//    //Estado S
//    M00 <= 11;
//    LX0 <= 0;
//    M10 <= 00;
//    M20 <= 11;
//    H0 <= 0;
//    LS0 <= 1;
//    LH0 <= 0;
//    #2;
//    $finish;
//end
//endmodule

src/BC.v
module BC(
    input inicio,
    input clk,
    input reset,
    output reg LX,
    output reg LS,
    output reg LH,
    output reg Hula,
    output reg[1:0] M0,
    output reg[1:0] M1,
    output reg[1:0] M2
);

reg[4:0] state;

parameter A = 5'b00000, B = 5'b00001, C = 5'b00010, D = 5'b00011, E = 5'b00100, F = 5'b00101, G = 5'b00110, H = 5'b00111, I = 5'b01000, J = 5'b01001, K = 5'b01010, L = 5'b01011, M = 5'b01100, N = 5'b01101, O = 5'b01110, P = 5'b01111, Q = 5'b10000, R = 5'b10001, S = 5'b10010, T = 5'b10011;

always @(posedge clk or reset)begin
    if (reset == 1 || inicio == 0) begin
        M0 <= 0;
        LX <= 0;
        M1 <= 0;
        M2 <= 0;
        Hula <= 0;
        LS <= 0;
        LH <= 0;
        state <= A;
    end
    else if (inicio == 1) begin
        case (state)
            A: begin
                M0 <= 0;
                LX <= 1;
                M1 <= 0;
                M2 <= 0;
                Hula <= 0;
                LS <= 0;
                LH <= 0;
                state <= B;
            end
            B: begin
                M0 <= 0;
                LX <= 0;
                M1 <= 1;
                M2 <= 0;
                Hula <= 0;
                LS <= 0;
                LH <= 0;
                state <= C;
            end
            C: begin
                M0 <= 0;
                LX <= 0;
                M1 <= 1;
                M2 <= 0;
                Hula <= 1;
                LS <= 0;
                LH <= 0;
                state <= D;
                end                    
            D: begin
                M0 <= 0;
                LX <= 0;
                M1 <= 1;
                M2 <= 0;
                Hula <= 1;
                LS <= 0;
                LH <= 1;
                state <= E;
            end
            E: begin
                M0 <= 1;
                LX <= 0;
                M1 <= 0;
                M2 <= 0;
                Hula <= 0;
                LS <= 0;
                LH <= 0;
                state <= F;
            end
            F: begin
                M0 <= 1;
                LX <= 0;
                M1 <= 0;
                M2 <= 3;
                Hula <= 0;
                LS <= 0;
                LH <= 0;
                state <= G;
            end
            G: begin
                M0 <= 1;
                LX <= 0;
                M1 <= 0;
                M2 <= 3;
                Hula <= 1;
                LS <= 0;
                LH <= 0;
                state <= H;
            end
            H: begin
                M0 <= 1;
                LX <= 0;
                M1 <= 0;
                M2 <= 3;
                Hula <= 1;
                LS <= 0;
                LH <= 1;
                state <= I;
            end
            I: begin
                M0 <= 2;
                LX <= 0;
                M1 <= 0;
                M2 <= 0;
                Hula <= 0;
                LS <= 0;
                LH <= 0;
                state <= J;
            end
            J: begin
                M0 <= 2;
                LX <= 0;
                M1 <= 0;
                M2 <= 0;
                Hula <= 0;
                LS <= 0;
                LH <= 0;
                state <= K;
            end
            K: begin
                M0 <= 2;
                LX <= 0;
                M1 <= 0;
                M2 <= 0;
                Hula <= 1;
                LS <= 0;
                LH <= 0;
                state <= L;
            end
            L: begin
                M0 <= 2;
                LX <= 0;
                M1 <= 0;
                M2 <= 0;
                Hula <= 1;
                LS <= 1;
                LH <= 0;
                state <= M;
            end
            M: begin
                M0 <= 0;
                LX <= 0;
                M1 <= 2;
                M2 <= 3;
                Hula <= 0;
                LS <= 0;
                LH <= 0;
                state <= N;
            end
            N: begin
                M0 <= 0;
                LX <= 0;
                M1 <= 2;
                M2 <= 3;
                Hula <= 0;
                LS <= 0;
                LH <= 0;
                state <= O;
            end
            O: begin
                M0 <= 0;
                LX <= 0;
                M1 <= 0;
                M2 <= 3;
                Hula <= 0;
                LS <= 0;
                LH <= 1;
                state <= P;
            end
            P: begin
                M0 <= 3;
                LX <= 0;
                M1 <= 0;
                M2 <= 0;
                Hula <= 0;
                LS <= 0;
                LH <= 0;
                state <= Q;
            end
            Q: begin
                M0 <= 3;
                LX <= 0;
                M1 <= 0;
                M2 <= 3;
                Hula <= 0;
                LS <= 0;
                LH <= 0;
                state <= R;
            end
            R: begin
                M0 <= 3;
                LX <= 0;
                M1 <= 0;
                M2 <= 3;
                Hula <= 0;
                LS <= 0;
                LH <= 0;
                state <= S;
            end
            S: begin
                M0 <= 3;
                LX <= 0;
                M1 <= 0;
                M2 <= 3;
                Hula <= 0;
                LS <= 1;
                LH <= 0;
                state <= T;
            end
            T: begin
                M0 <= 0;
                LX <= 0;
                M1 <= 0;
                M2 <= 0;
                Hula <= 0;
                LS <= 0;
                LH <= 0;
                state <= A;
            end
        endcase
    end
end

endmodule

//module testbench;
//
//    reg inicio0 = 0;
//    reg clk0 = 0;
//    reg reset0 = 0;
//    wire LX0;
//    wire LS0;
//    wire LH0;
//    wire H0;
//    wire [1:0] M00;
//    wire [1:0] M10;
//    wire [1:0] M20;
//
//BC jose(inicio0, clk0, reset0, LX0, LS0, LH0, H0, M00, M10, M20);
//
//always #1 begin
//    clk0 <= ~clk0;
//end
//
//initial begin
//    $dumpvars;
//    reset0 = 1;
//    #2;
//    reset0 = 0;
//    inicio0 = 1;
//    #100;
//    $finish;
//end
//endmodule

src/BOBC.v
`include "BC.v"
`include "BO.v"

module BOBC(
    input inicio,
    input rst,
    input clk,
    input [15:0] x,
    input [15:0] A,
    input [15:0] B,
    input [15:0] C,
    output [15:0] resultado
);

    wire [1:0] M0;
    wire clk;
    wire LX;
    wire rst;
    wire [1:0] M1;
    wire [1:0] M2;
    wire LH;
    wire LS;
    wire H;
    
    BC BC1(inicio, clk, rst, LX, LS, LH, H, M0, M1, M2);

    BO BO1(A, B, C, M0, x, clk, LX, rst, M1, M2, LH, LS, H, resultado);

endmodule 

module testbench;

    reg inicio0 = 0;
    reg rst0 = 0;
    reg clk0 = 0;
    reg [15:0] x0 = 3;
    reg [15:0] A0 = 1;
    reg [15:0] B0 = 1;
    reg [15:0] C0 = 2;
    wire[15:0] resultado0;

    BOBC BOCO1(inicio0, rst0, clk0, x0, A0, B0, C0, resultado0);

    always #1 begin
        clk0 <= ~clk0;
    end

    initial begin
        $dumpvars;
        rst0 <= 1;
        #1;
        rst0 <= 0;
        #2;
        inicio0 <= 1;
        #50;
        $finish;
    end
endmodule

src/dump.vcd
$date
	Tue Mar 29 17:56:42 2022
$end
$version
	Icarus Verilog
$end
$timescale
	1s
$end
$scope module testbench $end
$var wire 16 ! resultado0 [15:0] $end
$var reg 16 " A0 [15:0] $end
$var reg 16 # B0 [15:0] $end
$var reg 16 $ C0 [15:0] $end
$var reg 1 % clk0 $end
$var reg 1 & inicio0 $end
$var reg 1 ' rst0 $end
$var reg 16 ( x0 [15:0] $end
$scope module BOCO1 $end
$var wire 16 ) A [15:0] $end
$var wire 16 * B [15:0] $end
$var wire 16 + C [15:0] $end
$var wire 1 % clk $end
$var wire 1 & inicio $end
$var wire 1 ' rst $end
$var wire 16 , x [15:0] $end
$var wire 16 - resultado [15:0] $end
$var wire 2 . M2 [1:0] $end
$var wire 2 / M1 [1:0] $end
$var wire 2 0 M0 [1:0] $end
$var wire 1 1 LX $end
$var wire 1 2 LS $end
$var wire 1 3 LH $end
$var wire 1 4 H $end
$scope module BC1 $end
$var wire 1 % clk $end
$var wire 1 & inicio $end
$var wire 1 ' reset $end
$var reg 1 4 Hula $end
$var reg 1 3 LH $end
$var reg 1 2 LS $end
$var reg 1 1 LX $end
$var reg 2 5 M0 [1:0] $end
$var reg 2 6 M1 [1:0] $end
$var reg 2 7 M2 [1:0] $end
$var reg 5 8 state [4:0] $end
$upscope $end
$scope module BO1 $end
$var wire 16 9 A [15:0] $end
$var wire 16 : B [15:0] $end
$var wire 16 ; C [15:0] $end
$var wire 1 4 H $end
$var wire 1 3 LH $end
$var wire 1 2 LS $end
$var wire 1 1 LX $end
$var wire 2 < M0 [1:0] $end
$var wire 2 = M1 [1:0] $end
$var wire 2 > M2 [1:0] $end
$var wire 16 ? Pronto [15:0] $end
$var wire 1 % clk $end
$var wire 1 ' rst $end
$var wire 16 @ x [15:0] $end
$var wire 16 A saidaSM [15:0] $end
$var wire 16 B saidaR2 [15:0] $end
$var wire 16 C saidaR1 [15:0] $end
$var wire 16 D saidaR0 [15:0] $end
$var wire 16 E saidaM2 [15:0] $end
$var wire 16 F saidaM1 [15:0] $end
$var wire 16 G saidaM0 [15:0] $end
$scope module R0 $end
$var wire 16 H D [15:0] $end
$var wire 16 I Q [15:0] $end
$var wire 1 % clk $end
$var wire 1 1 load $end
$var wire 1 ' rst $end
$var reg 16 J saida [15:0] $end
$upscope $end
$scope module R1 $end
$var wire 16 K Q [15:0] $end
$var wire 1 % clk $end
$var wire 1 3 load $end
$var wire 1 ' rst $end
$var wire 16 L D [15:0] $end
$var reg 16 M saida [15:0] $end
$upscope $end
$scope module R2 $end
$var wire 1 % clk $end
$var wire 1 2 load $end
$var wire 1 ' rst $end
$var wire 16 N Q [15:0] $end
$var wire 16 O D [15:0] $end
$var reg 16 P saida [15:0] $end
$upscope $end
$scope module ULA $end
$var wire 1 4 H $end
$var wire 1 % clk $end
$var wire 16 Q resultado [15:0] $end
$var wire 16 R xis [15:0] $end
$var wire 16 S abc [15:0] $end
$var reg 16 T r [15:0] $end
$upscope $end
$scope module multiplexador0 $end
$var wire 16 U A [15:0] $end
$var wire 16 V B [15:0] $end
$var wire 16 W C [15:0] $end
$var wire 16 X D [15:0] $end
$var wire 1 % clk $end
$var wire 16 Y saidaM [15:0] $end
$var wire 2 Z set [1:0] $end
$var reg 16 [ s [15:0] $end
$upscope $end
$scope module multiplexador1 $end
$var wire 16 \ A [15:0] $end
$var wire 16 ] B [15:0] $end
$var wire 16 ^ C [15:0] $end
$var wire 16 _ D [15:0] $end
$var wire 1 % clk $end
$var wire 16 ` saidaM [15:0] $end
$var wire 2 a set [1:0] $end
$var reg 16 b s [15:0] $end
$upscope $end
$scope module multiplexador2 $end
$var wire 16 c A [15:0] $end
$var wire 16 d B [15:0] $end
$var wire 16 e C [15:0] $end
$var wire 16 f D [15:0] $end
$var wire 1 % clk $end
$var wire 16 g saidaM [15:0] $end
$var wire 2 h set [1:0] $end
$var reg 16 i s [15:0] $end
$upscope $end
$upscope $end
$upscope $end
$upscope $end
$enddefinitions $end
#0
$dumpvars
bx i
b0 h
bx g
b0 f
b0 e
bx d
b0 c
bx b
b0 a
bx `
b0 _
b0 ^
b0 ]
bx \
bx [
b0 Z
bx Y
b10 X
b1 W
b1 V
b0 U
bx T
bx S
bx R
bx Q
b0 P
bx O
b0 N
b0 M
bx L
b0 K
b0 J
b0 I
b11 H
bx G
bx F
bx E
b0 D
b0 C
b0 B
bx A
b11 @
b0 ?
b0 >
b0 =
b0 <
b10 ;
b1 :
b1 9
b0 8
b0 7
b0 6
b0 5
04
03
02
01
b0 0
b0 /
b0 .
b0 -
b11 ,
b10 +
b1 *
b1 )
b11 (
1'
0&
0%
b10 $
b1 #
b1 "
b0 !
$end
#1
b0 G
b0 Y
b0 \
b0 d
b0 [
b0 E
b0 R
b0 g
b0 i
0'
1%
#2
0%
#3
b1 8
11
b0 F
b0 S
b0 `
b0 b
1%
1&
#4
0%
#5
b10 8
b1 /
b1 6
b1 =
b1 a
01
b11 D
b11 I
b11 ]
b11 c
b11 J
b0 A
b0 L
b0 O
b0 Q
b0 T
1%
#6
0%
#7
b11 8
14
b11 F
b11 S
b11 `
b11 b
b11 E
b11 R
b11 g
b11 i
1%
#8
0%
#9
b100 8
13
b1001 A
b1001 L
b1001 O
b1001 Q
b1001 T
1%
#10
0%
#11
b1001 C
b1001 K
b1001 _
b1001 f
b1001 M
b101 8
03
04
b0 /
b0 6
b0 =
b0 a
b1 0
b1 5
b1 <
b1 Z
1%
#12
0%
#13
b110 8
b11 .
b11 7
b11 >
b11 h
b1 G
b1 Y
b1 \
b1 d
b1 [
b0 F
b0 S
b0 `
b0 b
b110 A
b110 L
b110 O
b110 Q
b110 T
1%
#14
0%
#15
b111 8
14
b11 A
b11 L
b11 O
b11 Q
b11 T
b1 F
b1 S
b1 `
b1 b
b1001 E
b1001 R
b1001 g
b1001 i
1%
#16
0%
#17
b1000 8
13
b1001 A
b1001 L
b1001 O
b1001 Q
b1001 T
1%
#18
0%
#19
b1001 8
03
04
b0 .
b0 7
b0 >
b0 h
b10 0
b10 5
b10 <
b10 Z
1%
#20
0%
#21
b1010 8
b11 E
b11 R
b11 g
b11 i
b1010 A
b1010 L
b1010 O
b1010 Q
b1010 T
1%
#22
0%
#23
b1011 8
14
b100 A
b100 L
b100 O
b100 Q
b100 T
1%
#24
0%
#25
b1100 8
12
b11 A
b11 L
b11 O
b11 Q
b11 T
1%
#26
0%
#27
b11 !
b11 -
b11 ?
b11 B
b11 N
b11 P
b11 ^
b11 e
b1101 8
02
04
b11 .
b11 7
b11 >
b11 h
b10 /
b10 6
b10 =
b10 a
b0 0
b0 5
b0 <
b0 Z
1%
#28
0%
#29
b1110 8
b0 G
b0 Y
b0 \
b0 d
b0 [
b1001 E
b1001 R
b1001 g
b1001 i
b11 F
b11 S
b11 `
b11 b
b100 A
b100 L
b100 O
b100 Q
b100 T
1%
#30
0%
#31
b1111 8
13
b0 /
b0 6
b0 =
b0 a
b1100 A
b1100 L
b1100 O
b1100 Q
b1100 T
1%
#32
0%
#33
b10000 8
03
b0 .
b0 7
b0 >
b0 h
b11 0
b11 5
b11 <
b11 Z
b1100 C
b1100 K
b1100 _
b1100 f
b1100 M
b0 F
b0 S
b0 `
b0 b
1%
#34
0%
#35
b10001 8
b11 .
b11 7
b11 >
b11 h
b1001 A
b1001 L
b1001 O
b1001 Q
b1001 T
b11 E
b11 R
b11 g
b11 i
b10 G
b10 Y
b10 \
b10 d
b10 [
1%
#36
0%
#37
b10010 8
b1100 E
b1100 R
b1100 g
b1100 i
b10 F
b10 S
b10 `
b10 b
b11 A
b11 L
b11 O
b11 Q
b11 T
1%
#38
0%
#39
b10011 8
12
b1110 A
b1110 L
b1110 O
b1110 Q
b1110 T
1%
#40
0%
#41
b0 8
02
b0 .
b0 7
b0 >
b0 h
b0 0
b0 5
b0 <
b0 Z
b1110 !
b1110 -
b1110 ?
b1110 B
b1110 N
b1110 P
b1110 ^
b1110 e
1%
#42
0%
#43
b1 8
11
b11 E
b11 R
b11 g
b11 i
b0 G
b0 Y
b0 \
b0 d
b0 [
1%
#44
0%
#45
b10 8
b1 /
b1 6
b1 =
b1 a
01
b0 F
b0 S
b0 `
b0 b
b101 A
b101 L
b101 O
b101 Q
b101 T
1%
#46
0%
#47
b11 8
14
b11 A
b11 L
b11 O
b11 Q
b11 T
b11 F
b11 S
b11 `
b11 b
1%
#48
0%
#49
b100 8
13
b1001 A
b1001 L
b1001 O
b1001 Q
b1001 T
1%
#50
0%
#51
b1001 C
b1001 K
b1001 _
b1001 f
b1001 M
b101 8
03
04
b0 /
b0 6
b0 =
b0 a
b1 0
b1 5
b1 <
b1 Z
1%
#52
0%
#53
b110 8
b11 .
b11 7
b11 >
b11 h
b1 G
b1 Y
b1 \
b1 d
b1 [
b0 F
b0 S
b0 `
b0 b
b110 A
b110 L
b110 O
b110 Q
b110 T
1%
