src/BC.v
module BC(
    input inicio,
    input clk,
    input reset,
    output reg LX,
    output reg LS,
    output reg LH,
    output reg H,
    output reg[1:0] M0,
    output reg[1:0] M1,
    output reg[1:0] M2
);

reg[2:0] state;

parameter A = 3'b000, B = 3'b001, C = 3'b010, D = 3'b011, E = 3'b100, F = 3'b101;

always @(posedge clk or reset)begin
    if (reset) begin
        state <= F;
    end
    else begin
        if (inicio == 1)begin
            state <= A;    
            case (state)
                A:begin  
                    M0 <= 0;
                    LX <= 1;
                    M1 <= 1;
                    M2 <= 0;
                    LS <= 0; 
                    LH <= 1; 
                    H <= 1;
                    state <= B;
                end    

                B:begin  
                    M0 <= 1;
                    LX <= 0;
                    M1 <= 0;
                    M2 <= 3;
                    LS <= 1; 
                    LH <= 0; 
                    H <= 1;
                    state <= C;
                end

                C:begin  
                    M0 <= 2;
                    LX <= 0;
                    M1 <= 0;
                    M2 <= 0;
                    LS <= 0; 
                    LH <= 1; 
                    H <= 1;
                    state <= D;
                end

                D:begin  
                    M0 <= 0;
                    LX <= 0;
                    M1 <= 2;
                    M2 <= 3;
                    LS <= 1; 
                    LH <= 0; 
                    H <= 0;
                    state <= E;
                end

                E:begin 
                    M0 <= 3;
                    LX <= 0;
                    M1 <= 0;
                    M2 <= 2;
                    LS <= 1; 
                    LH <= 0; 
                    H <= 0;
                    state <= F;
                end

                F:begin  M0 <= 0;
                    LX <= 0;
                    M1 <= 0;
                    M2 <= 0;
                    LS <= 0; 
                    LH <= 0; 
                    H <= 0;
                    state <= A;
                end
                
            endcase
        end
    end
end

endmodule

module testbench;

    reg inicio0 = 0;
    reg clk0 = 0;
    reg reset0 = 0;
    wire LX0;
    wire LS0;
    wire LH0;
    wire H0;
    wire [1:0] M00;
    wire [1:0] M10;
    wire [1:0] M20;

BC jose(inicio0, clk0, reset0, LX0, LS0, LH0, H0, M00, M10, M20);

always #1 begin
    clk0 <= ~clk0;
end

initial begin
    $dumpvars;
    #1;
    inicio0 <= 1;
    #50;
    $finish;
end
endmodule

src/dump.vcd
$date
	Sun Mar 27 12:53:40 2022
$end
$version
	Icarus Verilog
$end
$timescale
	1s
$end
$scope module testbench $end
$var wire 2 ! M20 [1:0] $end
$var wire 2 " M10 [1:0] $end
$var wire 2 # M00 [1:0] $end
$var wire 1 $ LX0 $end
$var wire 1 % LS0 $end
$var wire 1 & LH0 $end
$var wire 1 ' H0 $end
$var reg 1 ( clk0 $end
$var reg 1 ) inicio0 $end
$var reg 1 * reset0 $end
$scope module jose $end
$var wire 1 ( clk $end
$var wire 1 ) inicio $end
$var wire 1 * reset $end
$var reg 1 ' H $end
$var reg 1 & LH $end
$var reg 1 % LS $end
$var reg 1 $ LX $end
$var reg 2 + M0 [1:0] $end
$var reg 2 , M1 [1:0] $end
$var reg 2 - M2 [1:0] $end
$var reg 3 . state [2:0] $end
$upscope $end
$upscope $end
$enddefinitions $end
#0
$dumpvars
bx .
bx -
bx ,
bx +
0*
0)
0(
x'
x&
x%
x$
bx #
bx "
bx !
$end
#1
b0 .
1)
1(
#2
0(
#3
b1 .
1'
1&
0%
b0 !
b0 -
b1 "
b1 ,
1$
b0 #
b0 +
1(
#4
0(
#5
0&
1%
b11 !
b11 -
b0 "
b0 ,
0$
b1 #
b1 +
b10 .
1(
#6
0(
#7
1&
0%
b0 !
b0 -
b10 #
b10 +
b11 .
1(
#8
0(
#9
0'
0&
1%
b11 !
b11 -
b10 "
b10 ,
b0 #
b0 +
b100 .
1(
#10
0(
#11
b10 !
b10 -
b0 "
b0 ,
b11 #
b11 +
b101 .
1(
#12
0(
#13
0%
b0 !
b0 -
b0 #
b0 +
b0 .
1(
#14
0(
#15
b1 .
1'
1&
b1 "
b1 ,
1$
1(
#16
0(
#17
0&
1%
b11 !
b11 -
b0 "
b0 ,
0$
b1 #
b1 +
b10 .
1(
#18
0(
#19
1&
0%
b0 !
b0 -
b10 #
b10 +
b11 .
1(
#20
0(
#21
0'
0&
1%
b11 !
b11 -
b10 "
b10 ,
b0 #
b0 +
b100 .
1(
#22
0(
#23
b10 !
b10 -
b0 "
b0 ,
b11 #
b11 +
b101 .
1(
#24
0(
#25
0%
b0 !
b0 -
b0 #
b0 +
b0 .
1(
#26
0(
#27
b1 .
1'
1&
b1 "
b1 ,
1$
1(
#28
0(
#29
0&
1%
b11 !
b11 -
b0 "
b0 ,
0$
b1 #
b1 +
b10 .
1(
#30
0(
#31
1&
0%
b0 !
b0 -
b10 #
b10 +
b11 .
1(
#32
0(
#33
0'
0&
1%
b11 !
b11 -
b10 "
b10 ,
b0 #
b0 +
b100 .
1(
#34
0(
#35
b10 !
b10 -
b0 "
b0 ,
b11 #
b11 +
b101 .
1(
#36
0(
#37
0%
b0 !
b0 -
b0 #
b0 +
b0 .
1(
#38
0(
#39
b1 .
1'
1&
b1 "
b1 ,
1$
1(
#40
0(
#41
0&
1%
b11 !
b11 -
b0 "
b0 ,
0$
b1 #
b1 +
b10 .
1(
#42
0(
#43
1&
0%
b0 !
b0 -
b10 #
b10 +
b11 .
1(
#44
0(
#45
0'
0&
1%
b11 !
b11 -
b10 "
b10 ,
b0 #
b0 +
b100 .
1(
#46
0(
#47
b10 !
b10 -
b0 "
b0 ,
b11 #
b11 +
b101 .
1(
#48
0(
#49
0%
b0 !
b0 -
b0 #
b0 +
b0 .
1(
#50
0(
#51
b1 .
1'
1&
b1 "
b1 ,
1$
1(
