src/SomaMultiplica.v
module SomaMultiplica(
    input[15:0] abc,
    input[15:0] xis,
    input H,
    input clk,
    output[15:0] resultado
);

reg[15:0] r;

assign resultado = r;

always @(posedge clk) begin
    if (H == 1)begin
        r <= abc * xis;
    end
    else begin
        r <= abc + xis;
    end
end
endmodule

// module testbench;

//     reg[15:0] abc0;
//     reg[15:0] xis0;
//     reg H0 = 0;
//     reg clk0 = 0;
//     wire[15:0] resultado0;

// SomaMultiplica jose(abc0, xis0, H0, clk0, resultado0);

// always #1 begin
//     clk0 <= ~clk0;
// end

// initial begin
//     $dumpvars;
//     #1;
//     abc0 <= 2;
//     xis0 <= 3;
//     H0 <= 1;
//     #5;
//     $finish;
// end
// endmodule

src/Multiplexador.v
//Multiplexador do Bloco Operativo, será reutilizado em diferentes partes
module Multiplexador(
    input[15:0] A,
    input[15:0] B,
    input[15:0] C,
    input[15:0] D,
    input [1:0] set,
    input clk,
    output[15:0] saidaM
);

reg[15:0] s;

assign saidaM = s;
//A ordem das entradas importa nesse caso para setar as entradas no BO
always @(posedge clk) begin
    if (set == 0)begin
        s <= A;
    end
    if (set == 1)begin
        s <= B;
    end
    if (set == 2) begin
        s <= C;
    end
    if (set == 3) begin
        s <= D;
    end
end
endmodule

// module testbench;

//     reg [15:0] A0;
//     reg [15:0] B0;
//     reg [15:0] C0;
//     reg [15:0] D0;
//     reg [1:0] set0 = 0;
//     reg clk0 = 0;
//     wire [15:0] saida0;

// Multiplexador jose(A0, B0, C0, D0, set0, clk0, saida0);

// always #1 begin
//     clk0 <= ~clk0;
// end

// initial begin
//     $dumpvars;
//     #1;
//     A0 <= 1;
//     B0 <= 0;
//     C0 <= 3;
//     D0 <= 4;
//     set0 <= 1;
//     #5;
//     $finish;
// end
// endmodule

src/Registrador.v
module Registrador(
    input [15:0] D,
    input clk,
    input load,
    input rst,
    output [15:0] Q
);

    reg [15:0] saida;

    assign Q = saida;

    always @(posedge clk or rst) begin
        if (rst == 1) saida <= 0;
        else if (load == 1)begin
        saida <= D;
        end
    end
endmodule

// module testbench;

//     reg [15:0] D0;
//     reg clk0 = 0;
//     reg load0;
//     reg rst0 = 0;
//     wire [15:0] Q0;

// Registrador jose(D0, clk0, load0, rst0, Q0);

// always #1 begin
//     clk0 <= ~clk0;
// end

// initial begin
//     $dumpvars;
//     #1;
//     D0 <= 1;
//     load0 <= 1;
//     #5;
//     load0 <= 0;
//     D0 <= 5;
//     #5;
//     $finish;
// end
// endmodule

src/BO.v
`include "SomaMultiplica.v"
`include "Multiplexador.v"
`include "Registrador.v"

module BO (
    input [15:0] A,
    input [15:0] B,
    input [15:0] C,
    input [1:0] M0,
    input [15:0] x,
    input clk,
    input LX,
    input rst,
    input [1:0] M1,
    input [1:0] M2,
    input LH,
    input LS,
    input H,
    output [15:0] Pronto 
); 

wire [15:0] saidaR0;
Registrador R0(x, clk, LX, rst, saidaR0);

wire [15:0] saidaR1;
Registrador R1(saidaSM, clk, LH, rst, saidaR1);

wire [15:0] saidaR2;
Registrador R2(saidaSM, clk, LS, rst, saidaR2);

wire [15:0] saidaM0;
Multiplexador multiplexador0(0, A, B, C, M0, clk, saidaM0);

wire [15:0] saidaM1;
Multiplexador multiplexador1(saidaM0, saidaR0, saidaR1, saidaR2, M1, clk, saidaM1);

wire [15:0] saidaM2;
Multiplexador multiplexador2(saidaR0, saidaM0, saidaR1, saidaR2, M2, clk, saidaM2);

wire [15:0] saidaSM;
SomaMultiplica ULA(saidaM1, saidaM2, H, clk, saidaSM);

endmodule

module testbench;

    reg [15:0] A0 = 0;
    reg [15:0] B0 = 0;
    reg [15:0] C0 = 0;
    reg [1:0] M00;
    reg [15:0] D0 = 0;
    reg clk0 = 0;
    reg LX0;
    reg reset0;
    reg [1:0] M10;
    reg [1:0] M20;
    reg LH0 = 0;
    reg LS0 = 0;
    reg H0 = 0;
    wire [15:0] saida0;

BO jose(A0, B0, C0, M00, D0, clk0, LX0, reset0, M10, M20, LH0, LS0, H0, saida0);

always #1 begin
    clk0 <= ~clk0;
end

initial begin
    $dumpvars;
    #1;
    A0 <= 0;
    B0 <= 0;
    C0 <= 0;
    M00 <= 0;
    D0 <= 2;
    LX0 <= 1;
    reset0 <= 0;
    M10 <= 1;
    M20 <= 0;
    H0 <= 1;
    LS0 <= 0;
    LH0 <= 1;
    #1;
    A0 <= 3;
    B0 <= 0;
    C0 <= 0;
    M00 <= 1;
    D0 <= 0;
    LX0 <= 0;
    reset0 <= 0;
    M10 <= 0;
    M20 <= 3;
    H0 <= 1;
    LS0 <= 1;
    LH0 <= 0;
    #1;
    A0 <= 0;
    B0 <= 2;
    C0 <= 0;
    M00 <= 2;
    D0 <= 0;
    LX0 <= 0;
    reset0 <= 0;
    M10 <= 0;
    M20 <= 0;
    H0 <= 1;
    LS0 <= 0;
    LH0 <= 1;
    #1;
    A0 <= 0;
    B0 <= 0;
    C0 <= 0;
    M00 <= 0;
    D0 <= 0;
    LX0 <= 0;
    reset0 <= 0;
    M10 <= 2;
    M20 <= 3;
    H0 <= 0;
    LS0 <= 1;
    LH0 <= 0;
    #1;
    A0 <= 0;
    B0 <= 0;
    C0 <= 5;
    M00 <= 3;
    D0 <= 0;
    LX0 <= 0;
    reset0 <= 0;
    M10 <= 0;
    M20 <= 2;
    H0 <= 0;
    LS0 <= 1;
    LH0 <= 0;
    #1;
    A0 <= 0;
    B0 <= 0;
    C0 <= 0;
    M00 <= 0;
    D0 <= 0;
    LX0 <= 0;
    reset0 <= 1;
    M10 <= 0;
    M20 <= 0;
    H0 <= 0;
    LS0 <= 0;
    LH0 <= 0;
    #5;
    $finish;
end
endmodule

src/dump.vcd
$date
	Sun Mar 27 14:26:20 2022
$end
$version
	Icarus Verilog
$end
$timescale
	1s
$end
$scope module testbench $end
$var wire 16 ! saida0 [15:0] $end
$var reg 16 " A0 [15:0] $end
$var reg 16 # B0 [15:0] $end
$var reg 16 $ C0 [15:0] $end
$var reg 16 % D0 [15:0] $end
$var reg 1 & H0 $end
$var reg 1 ' LH0 $end
$var reg 1 ( LS0 $end
$var reg 1 ) LX0 $end
$var reg 2 * M00 [1:0] $end
$var reg 2 + M10 [1:0] $end
$var reg 2 , M20 [1:0] $end
$var reg 1 - clk0 $end
$var reg 1 . reset0 $end
$scope module jose $end
$var wire 16 / A [15:0] $end
$var wire 16 0 B [15:0] $end
$var wire 16 1 C [15:0] $end
$var wire 1 & H $end
$var wire 1 ' LH $end
$var wire 1 ( LS $end
$var wire 1 ) LX $end
$var wire 2 2 M0 [1:0] $end
$var wire 2 3 M1 [1:0] $end
$var wire 2 4 M2 [1:0] $end
$var wire 16 5 Pronto [15:0] $end
$var wire 1 - clk $end
$var wire 1 . rst $end
$var wire 16 6 x [15:0] $end
$var wire 16 7 saidaSM [15:0] $end
$var wire 16 8 saidaR2 [15:0] $end
$var wire 16 9 saidaR1 [15:0] $end
$var wire 16 : saidaR0 [15:0] $end
$var wire 16 ; saidaM2 [15:0] $end
$var wire 16 < saidaM1 [15:0] $end
$var wire 16 = saidaM0 [15:0] $end
$scope module R0 $end
$var wire 16 > D [15:0] $end
$var wire 16 ? Q [15:0] $end
$var wire 1 - clk $end
$var wire 1 ) load $end
$var wire 1 . rst $end
$var reg 16 @ saida [15:0] $end
$upscope $end
$scope module R1 $end
$var wire 16 A Q [15:0] $end
$var wire 1 - clk $end
$var wire 1 ' load $end
$var wire 1 . rst $end
$var wire 16 B D [15:0] $end
$var reg 16 C saida [15:0] $end
$upscope $end
$scope module R2 $end
$var wire 16 D Q [15:0] $end
$var wire 1 - clk $end
$var wire 1 ( load $end
$var wire 1 . rst $end
$var wire 16 E D [15:0] $end
$var reg 16 F saida [15:0] $end
$upscope $end
$scope module ULA $end
$var wire 1 & H $end
$var wire 1 - clk $end
$var wire 16 G resultado [15:0] $end
$var wire 16 H xis [15:0] $end
$var wire 16 I abc [15:0] $end
$var reg 16 J r [15:0] $end
$upscope $end
$scope module multiplexador0 $end
$var wire 16 K A [15:0] $end
$var wire 16 L B [15:0] $end
$var wire 16 M C [15:0] $end
$var wire 16 N D [15:0] $end
$var wire 1 - clk $end
$var wire 16 O saidaM [15:0] $end
$var wire 2 P set [1:0] $end
$var reg 16 Q s [15:0] $end
$upscope $end
$scope module multiplexador1 $end
$var wire 16 R A [15:0] $end
$var wire 16 S B [15:0] $end
$var wire 16 T C [15:0] $end
$var wire 16 U D [15:0] $end
$var wire 1 - clk $end
$var wire 16 V saidaM [15:0] $end
$var wire 2 W set [1:0] $end
$var reg 16 X s [15:0] $end
$upscope $end
$scope module multiplexador2 $end
$var wire 16 Y A [15:0] $end
$var wire 16 Z B [15:0] $end
$var wire 16 [ C [15:0] $end
$var wire 16 \ D [15:0] $end
$var wire 1 - clk $end
$var wire 16 ] saidaM [15:0] $end
$var wire 2 ^ set [1:0] $end
$var reg 16 _ s [15:0] $end
$upscope $end
$upscope $end
$upscope $end
$enddefinitions $end
#0
$dumpvars
bx _
bx ^
bx ]
bx \
bx [
bx Z
bx Y
bx X
bx W
bx V
bx U
bx T
bx S
bx R
bx Q
bx P
bx O
b0 N
b0 M
b0 L
b0 K
bx J
bx I
bx H
bx G
bx F
bx E
bx D
bx C
bx B
bx A
bx @
bx ?
b0 >
bx =
bx <
bx ;
bx :
bx 9
bx 8
bx 7
b0 6
bz 5
bx 4
bx 3
bx 2
b0 1
b0 0
b0 /
x.
0-
bx ,
bx +
bx *
x)
0(
0'
0&
b0 %
b0 $
b0 #
b0 "
bz !
$end
#1
b10 :
b10 ?
b10 S
b10 Y
b10 @
b0 =
b0 O
b0 R
b0 Z
b0 Q
1'
1&
b0 ,
b0 4
b0 ^
b1 +
b1 3
b1 W
0.
1)
b10 %
b10 6
b10 >
b0 *
b0 2
b0 P
1-
#2
0'
1(
b11 ,
b11 4
b11 ^
b0 +
b0 3
b0 W
0)
b0 %
b0 6
b0 >
b1 *
b1 2
b1 P
b11 "
b11 /
b11 L
0-
#3
b10 ;
b10 H
b10 ]
b10 _
b0 <
b0 I
b0 V
b0 X
b10 =
b10 O
b10 R
b10 Z
b10 Q
1'
0(
b0 ,
b0 4
b0 ^
b10 *
b10 2
b10 P
b10 #
b10 0
b10 M
b0 "
b0 /
b0 L
1-
#4
0'
1(
0&
b11 ,
b11 4
b11 ^
b10 +
b10 3
b10 W
b0 *
b0 2
b0 P
b0 #
b0 0
b0 M
0-
#5
b101 =
b101 O
b101 R
b101 Z
b101 Q
b10 <
b10 I
b10 V
b10 X
bx ;
bx H
bx ]
bx _
b10 7
b10 B
b10 E
b10 G
b10 J
b10 ,
b10 4
b10 ^
b0 +
b0 3
b0 W
b11 *
b11 2
b11 P
b101 $
b101 1
b101 N
1-
#6
b0 8
b0 D
b0 U
b0 \
b0 F
b0 9
b0 A
b0 T
b0 [
b0 C
b0 :
b0 ?
b0 S
b0 Y
b0 @
0(
b0 ,
b0 4
b0 ^
1.
b0 *
b0 2
b0 P
b0 $
b0 1
b0 N
0-
#7
bx 7
bx B
bx E
bx G
bx J
b0 ;
b0 H
b0 ]
b0 _
b101 <
b101 I
b101 V
b101 X
b0 =
b0 O
b0 R
b0 Z
b0 Q
1-
#8
0-
#9
b0 <
b0 I
b0 V
b0 X
b101 7
b101 B
b101 E
b101 G
b101 J
1-
#10
0-
#11
b0 7
b0 B
b0 E
b0 G
b0 J
1-
