src/SomaMultiplica.v
module SomaMultiplica(
    input[15:0] abc,
    input[15:0] xis,
    input H,
    input clk,
    output[15:0] resultado
);

reg[15:0] r;

assign resultado = r;

always @(posedge clk) begin
    if (H == 1)begin
        r <= abc * xis;
    end
    else begin
        r <= abc + xis;
    end
end
endmodule

// module testbench;

//     reg[15:0] abc0;
//     reg[15:0] xis0;
//     reg H0 = 0;
//     reg clk0 = 0;
//     wire[15:0] resultado0;

// SomaMultiplica jose(abc0, xis0, H0, clk0, resultado0);

// always #1 begin
//     clk0 <= ~clk0;
// end

// initial begin
//     $dumpvars;
//     #1;
//     abc0 <= 2;
//     xis0 <= 3;
//     H0 <= 1;
//     #5;
//     $finish;
// end
// endmodule

src/Multiplexador.v
//Multiplexador do Bloco Operativo, será reutilizado em diferentes partes
module Multiplexador(
    input[15:0] A,
    input[15:0] B,
    input[15:0] C,
    input[15:0] D,
    input [1:0] set,
    input clk,
    output[15:0] saidaM
);

reg[15:0] s;

assign saidaM = s;
//A ordem das entradas importa nesse caso para setar as entradas no BO
always @(posedge clk) begin
    if (set == 0)begin
        s <= A;
    end
    if (set == 1)begin
        s <= B;
    end
    if (set == 2) begin
        s <= C;
    end
    if (set == 3) begin
        s <= D;
    end
end
endmodule

// module testbench;

//     reg [15:0] A0;
//     reg [15:0] B0;
//     reg [15:0] C0;
//     reg [15:0] D0;
//     reg [1:0] set0 = 0;
//     reg clk0 = 0;
//     wire [15:0] saida0;

// Multiplexador jose(A0, B0, C0, D0, set0, clk0, saida0);

// always #1 begin
//     clk0 <= ~clk0;
// end

// initial begin
//     $dumpvars;
//     #1;
//     A0 <= 1;
//     B0 <= 0;
//     C0 <= 3;
//     D0 <= 4;
//     set0 <= 1;
//     #5;
//     $finish;
// end
// endmodule

src/Registrador.v
module Registrador(
    input [15:0] D,
    input clk,
    input load,
    input rst,
    output [15:0] Q
);

    reg [15:0] saida;

    assign Q = saida;

    always @(posedge clk or rst) begin
        if (rst == 1) saida <= 0;
        else if (load == 1)begin
        saida <= D;
        end
    end
endmodule

// module testbench;

//     reg [15:0] D0;
//     reg clk0 = 0;
//     reg load0;
//     reg rst0 = 0;
//     wire [15:0] Q0;

// Registrador jose(D0, clk0, load0, rst0, Q0);

// always #1 begin
//     clk0 <= ~clk0;
// end

// initial begin
//     $dumpvars;
//     #1;
//     D0 <= 1;
//     load0 <= 1;
//     #5;
//     load0 <= 0;
//     D0 <= 5;
//     #5;
//     $finish;
// end
// endmodule

src/BO.v
`include "SomaMultiplica.v"
`include "Multiplexador.v"
`include "Registrador.v"

module BO (
    input [15:0] A,
    input [15:0] B,
    input [15:0] C,
    input [1:0] M0,
    input [15:0] x,
    input clk,
    input LX,
    input rst,
    input [1:0] M1,
    input [1:0] M2,
    input LH,
    input LS,
    input H,
    output [15:0] Pronto 
); 

parameter vazio = 16'b0000000000000000;

Registrador R0(x, clk, LX, rst, saidaR0);
wire [15:0] saidaR0;

Registrador R1(saidaSM, clk, LH, rst, saidaR1);
wire [15:0] saidaR1;

Registrador R2(saidaSM, clk, LS, rst, saidaR2);
wire [15:0] saidaR2;

Multiplexador multiplexador0(vazio, A, B, C, M0, clk, saidaM0);
wire [15:0] saidaM0;

Multiplexador multiplexador2(saidaR0, saidaM0, saidaR2, saidaR1, M2, clk, saidaM2);
wire [15:0] saidaM2;

Multiplexador multiplexador1(saidaM0, saidaR0, saidaR2, saidaR1, M1, clk, saidaM1);
wire [15:0] saidaM1;

SomaMultiplica ULA(saidaM1, saidaM2, H, clk, saidaSM);
wire [15:0] saidaSM;

assign Pronto = saidaR2;

endmodule

//module testbench;
//
//    reg [15:0] A0 = 1;
//    reg [15:0] B0 = 2;
//    reg [15:0] C0 = 2;
//    reg [1:0] M00;
//    reg [15:0] x0 = 2;
//    reg clk0 = 0;
//    reg LX0;
//    reg reset0;
//    reg [1:0] M10;
//    reg [1:0] M20;
//    reg LH0 = 0;
//    reg LS0 = 0;
//    reg H0 = 0;
//    wire [15:0] saida0;
//
//BO jose(A0, B0, C0, M00, x0, clk0, LX0, reset0, M10, M20, LH0, LS0, H0, saida0);
//
//always #1 begin
//    clk0 <= ~clk0;
//end
//
//initial begin
//    $dumpvars;
//    #1;
//    M00 <= 00;
//    LX0 <= 1;
//    reset0 <= 0;
//    M10 <= 01;
//    M20 <= 00;
//    H0 <= 1;
//    LS0 <= 0;
//    LH0 <= 1;
//    #6;
//    M00 <= 01;
//    LX0 <= 0;
//    reset0 <= 0;
//    M10 <= 00;
//    M20 <= 11;
//    H0 <= 1;
//    LS0 <= 1;
//    LH0 <= 0;
//    #6;
//    M00 <= 10;
//    LX0 <= 0;
//    reset0 <= 0;
//    M10 <= 00;
//    M20 <= 00;
//    H0 <= 1;
//    LS0 <= 0;
//    LH0 <= 1;
//    #8;
//    M00 <= 00;
//    LX0 <= 0;
//    reset0 <= 0;
//    M10 <= 10;
//    M20 <= 11;
//    H0 <= 0;
//    LS0 <= 1;
//    LH0 <= 0;
//    #6;
//    M00 <= 11;
//    LX0 <= 0;
//    reset0 <= 0;
//    M10 <= 00;
//    M20 <= 10;
//    H0 <= 0;
//    LS0 <= 1;
//    LH0 <= 0;
//    #8;
//    M00 <= 00;
//    LX0 <= 0;
//    reset0 <= 1;
//    M10 <= 00;
//    M20 <= 00;
//    H0 <= 0;
//    LS0 <= 0;
//    LH0 <= 0;
//    #50;
//    $finish;
//end
//endmodule

src/BC.v
module BC(
    input inicio,
    input clk,
    input reset,
    output reg LX,
    output reg LS,
    output reg LH,
    output reg H,
    output reg[1:0] M0,
    output reg[1:0] M1,
    output reg[1:0] M2
);

reg[2:0] state;

parameter A = 3'b000, B = 3'b001, C = 3'b010, D = 3'b011, E = 3'b100, F = 3'b101;

always @(posedge clk or reset)begin
    if (reset) begin
        state <= F;
    end
    else begin
        if (inicio == 1)begin
            state <= A;    
            case (state)
                A:begin  
                    M0 <= 0;
                    LX <= 1;
                    M1 <= 1;
                    M2 <= 0;
                    LS <= 0; 
                    LH <= 1; 
                    H <= 1;
                    state <= B;
                end    

                B:begin  
                    M0 <= 1;
                    LX <= 0;
                    M1 <= 0;
                    M2 <= 3;
                    LS <= 1; 
                    LH <= 0; 
                    H <= 1;
                    state <= C;
                end

                C:begin  
                    M0 <= 2;
                    LX <= 0;
                    M1 <= 0;
                    M2 <= 0;
                    LS <= 0; 
                    LH <= 1; 
                    H <= 1;
                    state <= D;
                end

                D:begin  
                    M0 <= 0;
                    LX <= 0;
                    M1 <= 2;
                    M2 <= 3;
                    LS <= 1; 
                    LH <= 0; 
                    H <= 0;
                    state <= E;
                end

                E:begin 
                    M0 <= 3;
                    LX <= 0;
                    M1 <= 0;
                    M2 <= 2;
                    LS <= 1; 
                    LH <= 0; 
                    H <= 0;
                    state <= F;
                end

                F:begin  M0 <= 0;
                    LX <= 0;
                    M1 <= 0;
                    M2 <= 0;
                    LS <= 0; 
                    LH <= 0; 
                    H <= 0;
                    state <= A;
                end
                
            endcase
        end
    end
end

endmodule

//module testbench;
//
//    reg inicio0 = 0;
//    reg clk0 = 0;
//    reg reset0 = 0;
//    wire LX0;
//    wire LS0;
//    wire LH0;
//    wire H0;
//    wire [1:0] M00;
//    wire [1:0] M10;
//    wire [1:0] M20;
//
//BC jose(inicio0, clk0, reset0, LX0, LS0, LH0, H0, M00, M10, M20);
//
//always #1 begin
//    clk0 <= ~clk0;
//end
//
//initial begin
//    $dumpvars;
//    #1;
//    inicio0 <= 1;
//    #13;
//    $finish;
//end
//endmodule

src/BOBC.v
`include "BC.v"
`include "BO.v"

module BOBC(
    input inicio,
    input rst,
    input clk,
    input [15:0] x,
    input [15:0] A,
    input [15:0] B,
    input [15:0] C,
    output [15:0] resultado
);

    wire [1:0] M0;
    wire clk;
    wire LX;
    wire rst;
    wire [1:0] M1;
    wire [1:0] M2;
    wire LH;
    wire LS;
    wire H;
    
    BC BC1(inicio, clk, rst, LX, LS, LH, H, M0, M1, M2);

    BO BO1(A, B, C, M0, x, clk, LX, rst, M1, M2, LH, LS, H, resultado);

endmodule 

module testbench;

    reg inicio0 = 0;
    reg rst0 = 0;
    reg clk0 = 0;
    reg [15:0] x0 = 2;
    reg [15:0] A0 = 1;
    reg [15:0] B0 = 2;
    reg [15:0] C0 = 2;
    wire[15:0] resultado0;

    BOBC BOCO1(inicio0, rst0, clk0, x0, A0, B0, C0, resultado0);

    always #1 begin
        clk0 <= ~clk0;
    end

    initial begin
        $dumpvars;
        #1;
        inicio0 <= 0;
        #50;
        inicio0 <= 1;
        #55;
        $finish;
    end
endmodule

src/dump.vcd
$date
	Sun Mar 27 20:23:27 2022
$end
$version
	Icarus Verilog
$end
$timescale
	1s
$end
$scope module testbench $end
$var wire 16 ! resultado0 [15:0] $end
$var reg 16 " A0 [15:0] $end
$var reg 16 # B0 [15:0] $end
$var reg 16 $ C0 [15:0] $end
$var reg 1 % clk0 $end
$var reg 1 & inicio0 $end
$var reg 1 ' rst0 $end
$var reg 16 ( x0 [15:0] $end
$scope module BOCO1 $end
$var wire 16 ) A [15:0] $end
$var wire 16 * B [15:0] $end
$var wire 16 + C [15:0] $end
$var wire 1 % clk $end
$var wire 1 & inicio $end
$var wire 1 ' rst $end
$var wire 16 , x [15:0] $end
$var wire 16 - resultado [15:0] $end
$var wire 2 . M2 [1:0] $end
$var wire 2 / M1 [1:0] $end
$var wire 2 0 M0 [1:0] $end
$var wire 1 1 LX $end
$var wire 1 2 LS $end
$var wire 1 3 LH $end
$var wire 1 4 H $end
$scope module BC1 $end
$var wire 1 % clk $end
$var wire 1 & inicio $end
$var wire 1 ' reset $end
$var reg 1 4 H $end
$var reg 1 3 LH $end
$var reg 1 2 LS $end
$var reg 1 1 LX $end
$var reg 2 5 M0 [1:0] $end
$var reg 2 6 M1 [1:0] $end
$var reg 2 7 M2 [1:0] $end
$var reg 3 8 state [2:0] $end
$upscope $end
$scope module BO1 $end
$var wire 16 9 A [15:0] $end
$var wire 16 : B [15:0] $end
$var wire 16 ; C [15:0] $end
$var wire 1 4 H $end
$var wire 1 3 LH $end
$var wire 1 2 LS $end
$var wire 1 1 LX $end
$var wire 2 < M0 [1:0] $end
$var wire 2 = M1 [1:0] $end
$var wire 2 > M2 [1:0] $end
$var wire 16 ? Pronto [15:0] $end
$var wire 1 % clk $end
$var wire 1 ' rst $end
$var wire 16 @ x [15:0] $end
$var wire 16 A saidaSM [15:0] $end
$var wire 16 B saidaR2 [15:0] $end
$var wire 16 C saidaR1 [15:0] $end
$var wire 16 D saidaR0 [15:0] $end
$var wire 16 E saidaM2 [15:0] $end
$var wire 16 F saidaM1 [15:0] $end
$var wire 16 G saidaM0 [15:0] $end
$scope module R0 $end
$var wire 16 H D [15:0] $end
$var wire 16 I Q [15:0] $end
$var wire 1 % clk $end
$var wire 1 1 load $end
$var wire 1 ' rst $end
$var reg 16 J saida [15:0] $end
$upscope $end
$scope module R1 $end
$var wire 16 K Q [15:0] $end
$var wire 1 % clk $end
$var wire 1 3 load $end
$var wire 1 ' rst $end
$var wire 16 L D [15:0] $end
$var reg 16 M saida [15:0] $end
$upscope $end
$scope module R2 $end
$var wire 1 % clk $end
$var wire 1 2 load $end
$var wire 1 ' rst $end
$var wire 16 N Q [15:0] $end
$var wire 16 O D [15:0] $end
$var reg 16 P saida [15:0] $end
$upscope $end
$scope module ULA $end
$var wire 1 4 H $end
$var wire 1 % clk $end
$var wire 16 Q resultado [15:0] $end
$var wire 16 R xis [15:0] $end
$var wire 16 S abc [15:0] $end
$var reg 16 T r [15:0] $end
$upscope $end
$scope module multiplexador0 $end
$var wire 16 U A [15:0] $end
$var wire 16 V B [15:0] $end
$var wire 16 W C [15:0] $end
$var wire 16 X D [15:0] $end
$var wire 1 % clk $end
$var wire 16 Y saidaM [15:0] $end
$var wire 2 Z set [1:0] $end
$var reg 16 [ s [15:0] $end
$upscope $end
$scope module multiplexador1 $end
$var wire 16 \ A [15:0] $end
$var wire 16 ] B [15:0] $end
$var wire 16 ^ C [15:0] $end
$var wire 16 _ D [15:0] $end
$var wire 1 % clk $end
$var wire 16 ` saidaM [15:0] $end
$var wire 2 a set [1:0] $end
$var reg 16 b s [15:0] $end
$upscope $end
$scope module multiplexador2 $end
$var wire 16 c A [15:0] $end
$var wire 16 d B [15:0] $end
$var wire 16 e C [15:0] $end
$var wire 16 f D [15:0] $end
$var wire 1 % clk $end
$var wire 16 g saidaM [15:0] $end
$var wire 2 h set [1:0] $end
$var reg 16 i s [15:0] $end
$upscope $end
$upscope $end
$upscope $end
$upscope $end
$enddefinitions $end
#0
$dumpvars
bx i
bx h
bx g
bx f
bx e
bx d
bx c
bx b
bx a
bx `
bx _
bx ^
bx ]
bx \
bx [
bx Z
bx Y
b10 X
b10 W
b1 V
b0 U
bx T
bx S
bx R
bx Q
bx P
bx O
bx N
bx M
bx L
bx K
bx J
bx I
b10 H
bx G
bx F
bx E
bx D
bx C
bx B
bx A
b10 @
bx ?
bx >
bx =
bx <
b10 ;
b10 :
b1 9
bx 8
bx 7
bx 6
bx 5
x4
x3
x2
x1
bx 0
bx /
bx .
bx -
b10 ,
b10 +
b10 *
b1 )
b10 (
0'
0&
0%
b10 $
b10 #
b1 "
bx !
$end
#1
1%
#2
0%
#3
1%
#4
0%
#5
1%
#6
0%
#7
1%
#8
0%
#9
1%
#10
0%
#11
1%
#12
0%
#13
1%
#14
0%
#15
1%
#16
0%
#17
1%
#18
0%
#19
1%
#20
0%
#21
1%
#22
0%
#23
1%
#24
0%
#25
1%
#26
0%
#27
1%
#28
0%
#29
1%
#30
0%
#31
1%
#32
0%
#33
1%
#34
0%
#35
1%
#36
0%
#37
1%
#38
0%
#39
1%
#40
0%
#41
1%
#42
0%
#43
1%
#44
0%
#45
1%
#46
0%
#47
1%
#48
0%
#49
1%
#50
0%
#51
b0 8
1%
1&
#52
0%
#53
b1 8
14
13
02
b0 .
b0 7
b0 >
b0 h
b1 /
b1 6
b1 =
b1 a
11
b0 0
b0 5
b0 <
b0 Z
1%
#54
0%
#55
03
12
b11 .
b11 7
b11 >
b11 h
b0 /
b0 6
b0 =
b0 a
01
b1 0
b1 5
b1 <
b1 Z
b10 8
b10 D
b10 I
b10 ]
b10 c
b10 J
b0 G
b0 Y
b0 \
b0 d
b0 [
1%
#56
0%
#57
13
02
b0 .
b0 7
b0 >
b0 h
b10 0
b10 5
b10 <
b10 Z
b11 8
b1 G
b1 Y
b1 \
b1 d
b1 [
b0 F
b0 S
b0 `
b0 b
1%
#58
0%
#59
04
03
12
b11 .
b11 7
b11 >
b11 h
b10 /
b10 6
b10 =
b10 a
b0 0
b0 5
b0 <
b0 Z
b100 8
b1 F
b1 S
b1 `
b1 b
b10 E
b10 R
b10 g
b10 i
b10 G
b10 Y
b10 \
b10 d
b10 [
1%
#60
0%
#61
b10 .
b10 7
b10 >
b10 h
b0 /
b0 6
b0 =
b0 a
b11 0
b11 5
b11 <
b11 Z
b101 8
b0 G
b0 Y
b0 \
b0 d
b0 [
bx E
bx R
bx g
bx i
bx F
bx S
bx `
bx b
b11 A
b11 L
b11 O
b11 Q
b11 T
1%
#62
0%
#63
02
b0 .
b0 7
b0 >
b0 h
b0 0
b0 5
b0 <
b0 Z
b0 8
b11 !
b11 -
b11 ?
b11 B
b11 N
b11 P
b11 ^
b11 e
bx A
bx L
bx O
bx Q
bx T
b0 F
b0 S
b0 `
b0 b
b10 G
b10 Y
b10 \
b10 d
b10 [
1%
#64
0%
#65
b1 8
14
13
b1 /
b1 6
b1 =
b1 a
11
b0 G
b0 Y
b0 \
b0 d
b0 [
b10 E
b10 R
b10 g
b10 i
b10 F
b10 S
b10 `
b10 b
1%
#66
0%
#67
03
12
b11 .
b11 7
b11 >
b11 h
b0 /
b0 6
b0 =
b0 a
01
b1 0
b1 5
b1 <
b1 Z
b10 8
b100 A
b100 L
b100 O
b100 Q
b100 T
1%
#68
0%
#69
b100 !
b100 -
b100 ?
b100 B
b100 N
b100 P
b100 ^
b100 e
13
02
b0 .
b0 7
b0 >
b0 h
b10 0
b10 5
b10 <
b10 Z
b11 8
b1 G
b1 Y
b1 \
b1 d
b1 [
bx E
bx R
bx g
bx i
b0 F
b0 S
b0 `
b0 b
1%
#70
0%
#71
04
03
12
b11 .
b11 7
b11 >
b11 h
b10 /
b10 6
b10 =
b10 a
b0 0
b0 5
b0 <
b0 Z
b100 8
b100 C
b100 K
b100 _
b100 f
b100 M
bx A
bx L
bx O
bx Q
bx T
b1 F
b1 S
b1 `
b1 b
b10 E
b10 R
b10 g
b10 i
b10 G
b10 Y
b10 \
b10 d
b10 [
1%
#72
0%
#73
bx !
bx -
bx ?
bx B
bx N
bx P
bx ^
bx e
b10 .
b10 7
b10 >
b10 h
b0 /
b0 6
b0 =
b0 a
b11 0
b11 5
b11 <
b11 Z
b101 8
b0 G
b0 Y
b0 \
b0 d
b0 [
b100 E
b100 R
b100 g
b100 i
b100 F
b100 S
b100 `
b100 b
b11 A
b11 L
b11 O
b11 Q
b11 T
1%
#74
0%
#75
02
b0 .
b0 7
b0 >
b0 h
b0 0
b0 5
b0 <
b0 Z
b0 8
b11 !
b11 -
b11 ?
b11 B
b11 N
b11 P
b11 ^
b11 e
b1000 A
b1000 L
b1000 O
b1000 Q
b1000 T
b0 F
b0 S
b0 `
b0 b
bx E
bx R
bx g
bx i
b10 G
b10 Y
b10 \
b10 d
b10 [
1%
#76
0%
#77
b1 8
14
13
b1 /
b1 6
b1 =
b1 a
11
b0 G
b0 Y
b0 \
b0 d
b0 [
b10 E
b10 R
b10 g
b10 i
b10 F
b10 S
b10 `
b10 b
bx A
bx L
bx O
bx Q
bx T
1%
#78
0%
#79
03
12
b11 .
b11 7
b11 >
b11 h
b0 /
b0 6
b0 =
b0 a
01
b1 0
b1 5
b1 <
b1 Z
b10 8
bx C
bx K
bx _
bx f
bx M
b100 A
b100 L
b100 O
b100 Q
b100 T
1%
#80
0%
#81
b100 !
b100 -
b100 ?
b100 B
b100 N
b100 P
b100 ^
b100 e
13
02
b0 .
b0 7
b0 >
b0 h
b10 0
b10 5
b10 <
b10 Z
b11 8
b1 G
b1 Y
b1 \
b1 d
b1 [
bx E
bx R
bx g
bx i
b0 F
b0 S
b0 `
b0 b
1%
#82
0%
#83
04
03
12
b11 .
b11 7
b11 >
b11 h
b10 /
b10 6
b10 =
b10 a
b0 0
b0 5
b0 <
b0 Z
b100 8
b100 C
b100 K
b100 _
b100 f
b100 M
bx A
bx L
bx O
bx Q
bx T
b1 F
b1 S
b1 `
b1 b
b10 E
b10 R
b10 g
b10 i
b10 G
b10 Y
b10 \
b10 d
b10 [
1%
#84
0%
#85
bx !
bx -
bx ?
bx B
bx N
bx P
bx ^
bx e
b10 .
b10 7
b10 >
b10 h
b0 /
b0 6
b0 =
b0 a
b11 0
b11 5
b11 <
b11 Z
b101 8
b0 G
b0 Y
b0 \
b0 d
b0 [
b100 E
b100 R
b100 g
b100 i
b100 F
b100 S
b100 `
b100 b
b11 A
b11 L
b11 O
b11 Q
b11 T
1%
#86
0%
#87
02
b0 .
b0 7
b0 >
b0 h
b0 0
b0 5
b0 <
b0 Z
b0 8
b11 !
b11 -
b11 ?
b11 B
b11 N
b11 P
b11 ^
b11 e
b1000 A
b1000 L
b1000 O
b1000 Q
b1000 T
b0 F
b0 S
b0 `
b0 b
bx E
bx R
bx g
bx i
b10 G
b10 Y
b10 \
b10 d
b10 [
1%
#88
0%
#89
b1 8
14
13
b1 /
b1 6
b1 =
b1 a
11
b0 G
b0 Y
b0 \
b0 d
b0 [
b10 E
b10 R
b10 g
b10 i
b10 F
b10 S
b10 `
b10 b
bx A
bx L
bx O
bx Q
bx T
1%
#90
0%
#91
03
12
b11 .
b11 7
b11 >
b11 h
b0 /
b0 6
b0 =
b0 a
01
b1 0
b1 5
b1 <
b1 Z
b10 8
bx C
bx K
bx _
bx f
bx M
b100 A
b100 L
b100 O
b100 Q
b100 T
1%
#92
0%
#93
b100 !
b100 -
b100 ?
b100 B
b100 N
b100 P
b100 ^
b100 e
13
02
b0 .
b0 7
b0 >
b0 h
b10 0
b10 5
b10 <
b10 Z
b11 8
b1 G
b1 Y
b1 \
b1 d
b1 [
bx E
bx R
bx g
bx i
b0 F
b0 S
b0 `
b0 b
1%
#94
0%
#95
04
03
12
b11 .
b11 7
b11 >
b11 h
b10 /
b10 6
b10 =
b10 a
b0 0
b0 5
b0 <
b0 Z
b100 8
b100 C
b100 K
b100 _
b100 f
b100 M
bx A
bx L
bx O
bx Q
bx T
b1 F
b1 S
b1 `
b1 b
b10 E
b10 R
b10 g
b10 i
b10 G
b10 Y
b10 \
b10 d
b10 [
1%
#96
0%
#97
bx !
bx -
bx ?
bx B
bx N
bx P
bx ^
bx e
b10 .
b10 7
b10 >
b10 h
b0 /
b0 6
b0 =
b0 a
b11 0
b11 5
b11 <
b11 Z
b101 8
b0 G
b0 Y
b0 \
b0 d
b0 [
b100 E
b100 R
b100 g
b100 i
b100 F
b100 S
b100 `
b100 b
b11 A
b11 L
b11 O
b11 Q
b11 T
1%
#98
0%
#99
02
b0 .
b0 7
b0 >
b0 h
b0 0
b0 5
b0 <
b0 Z
b0 8
b11 !
b11 -
b11 ?
b11 B
b11 N
b11 P
b11 ^
b11 e
b1000 A
b1000 L
b1000 O
b1000 Q
b1000 T
b0 F
b0 S
b0 `
b0 b
bx E
bx R
bx g
bx i
b10 G
b10 Y
b10 \
b10 d
b10 [
1%
#100
0%
#101
b1 8
14
13
b1 /
b1 6
b1 =
b1 a
11
b0 G
b0 Y
b0 \
b0 d
b0 [
b10 E
b10 R
b10 g
b10 i
b10 F
b10 S
b10 `
b10 b
bx A
bx L
bx O
bx Q
bx T
1%
#102
0%
#103
03
12
b11 .
b11 7
b11 >
b11 h
b0 /
b0 6
b0 =
b0 a
01
b1 0
b1 5
b1 <
b1 Z
b10 8
bx C
bx K
bx _
bx f
bx M
b100 A
b100 L
b100 O
b100 Q
b100 T
1%
#104
0%
#105
b100 !
b100 -
b100 ?
b100 B
b100 N
b100 P
b100 ^
b100 e
13
02
b0 .
b0 7
b0 >
b0 h
b10 0
b10 5
b10 <
b10 Z
b11 8
b1 G
b1 Y
b1 \
b1 d
b1 [
bx E
bx R
bx g
bx i
b0 F
b0 S
b0 `
b0 b
1%
